python_qlv_helper-0.9.6.dist-info/licenses/LICENSE
qlv_helper/__init__.py
qlv_helper/config/__init__.py
qlv_helper/config/custom_exception.py
qlv_helper/config/url_const.py
qlv_helper/controller/__init__.py
qlv_helper/controller/domestic_activity_order.py
qlv_helper/controller/main_page.py
qlv_helper/controller/order_detail.py
qlv_helper/controller/order_table.py
qlv_helper/controller/user_login.py
qlv_helper/controller/wechat_login.py
qlv_helper/http/__init__.py
qlv_helper/http/main_page.py
qlv_helper/http/order_page.py
qlv_helper/http/order_table_page.py
qlv_helper/po/__init__.py
qlv_helper/po/domestic_activity_order_page.py
qlv_helper/po/login_page.py
qlv_helper/po/main_page.py
qlv_helper/po/order_detail_page.py
qlv_helper/po/wechat_auth_page.py
qlv_helper/utils/__init__.py
qlv_helper/utils/browser_utils.py
qlv_helper/utils/datetime_utils.py
qlv_helper/utils/file_handle.py
qlv_helper/utils/html_utils.py
qlv_helper/utils/ocr_helper.py
qlv_helper/utils/po_utils.py
qlv_helper/utils/stealth_browser.py
qlv_helper/utils/type_utils.py
qlv_helper/utils/windows_utils.py
python_qlv_helper-0.9.6.dist-info/METADATA
python_qlv_helper-0.9.6.dist-info/WHEEL
python_qlv_helper-0.9.6.dist-info/top_level.txt
python_qlv_helper-0.9.6.dist-info/RECORD
