Metadata-Version: 2.4
Name: python_qlv_helper
Version: 0.9.6
Summary: qlv helper python package
Author-email: ckf10000 <ckf10000@sina.com>
License:                                  Apache License
Project-URL: Homepage, https://github.com/ckf10000/qlv-helper
Project-URL: Source, https://github.com/ckf10000/qlv-helper
Project-URL: Issues, https://github.com/ckf10000/qlv-helper/issues
Requires-Python: >=3.12
License-File: LICENSE
Requires-Dist: playwright==1.56.0; python_version >= "3.12"
Requires-Dist: playwright-stealth==2.0.0; python_version >= "3.12"
Requires-Dist: ddddocr==1.5.6; python_version >= "3.12"
Requires-Dist: aiohttp==3.13.2; python_version >= "3.12"
Requires-Dist: beautifulsoup4==4.14.2; python_version >= "3.12"
Requires-Dist: airtest==1.3.6; python_version >= "3.12"
Requires-Dist: python_http_helper>=0.2.2; python_version >= "3.12"
Requires-Dist: python_playwright_helper>=0.4.3; python_version >= "3.12"
Requires-Dist: python_ocr_helper>=0.0.2; python_version >= "3.12"
Requires-Dist: flight_helper>=0.3.8
Dynamic: license-file
